taskManager/AWSNotifier.py
taskManager/Notifier.py
taskManager/ProcessHandler.py
taskManager/ResourceMonitor.py
taskManager/__init__.py
taskManager/config_helpers.py
taskManager/monitor_resource_monitor.py
taskManager/plot_resource_usage.py
taskManager/plotting.py
taskManager/resource_monitor.py
taskManager/utils/__init__.py
taskManager/utils/config.py
taskManager/utils/mail.py
taskManager-0.2.1.data/scripts/monitor_resource_monitor.py
taskManager-0.2.1.data/scripts/plot_resource_usage.py
taskManager-0.2.1.data/scripts/resource_monitor.py
taskManager-0.2.1.data/scripts/taskManager
taskManager-0.2.1.dist-info/LICENSE
taskManager-0.2.1.dist-info/METADATA
taskManager-0.2.1.dist-info/WHEEL
taskManager-0.2.1.dist-info/top_level.txt
taskManager-0.2.1.dist-info/zip-safe
taskManager-0.2.1.dist-info/RECORD
