Metadata-Version: 2.1
Name: taskManager
Version: 0.2.1
Summary: Task manager to keep track of compute resources and send email update when command exits
Home-page: https://github.com/rlorigro/TaskManager
Author: Ryan Lorig-Roach, Andrew Bailey
Author-email: rlorigro@ucsc.edu, andbaile@ucsc.com
License: MIT
Platform: UNKNOWN
Requires-Dist: psutil (>=5.6.1)
Requires-Dist: boto3 (>=1.9)
Requires-Dist: pytest (>=4.3.1)
Requires-Dist: matplotlib (>=2.0.2)
